{
  "run_id": "cap-2026-03-25",
  "run_date": "2026-03-25",
  "scan_mode": "mock",
  "url_limit": 27,
  "scan_summary": {
    "total": 27,
    "succeeded": 27,
    "failed": 0,
    "excluded": 0
  },
  "benchmark_summary": {
    "means": {
      "performance_score": 66.33,
      "accessibility_score": 78.96,
      "best_practices_score": 74.33,
      "seo_score": 77.15
    },
    "url_counts": {
      "total": 27,
      "succeeded": 27,
      "failed": 0
    }
  },
  "bilingual_parity": {
    "pairs": [
      {
        "id": "curated-001",
        "accessibility_gap": -14
      },
      {
        "id": "curated-002",
        "accessibility_gap": -14
      },
      {
        "id": "curated-004",
        "accessibility_gap": -14
      },
      {
        "id": "curated-006",
        "accessibility_gap": -14
      },
      {
        "id": "curated-008",
        "accessibility_gap": -14
      },
      {
        "id": "curated-010",
        "accessibility_gap": -14
      },
      {
        "id": "top-task-1",
        "accessibility_gap": -14
      },
      {
        "id": "top-task-2",
        "accessibility_gap": -14
      },
      {
        "id": "top-task-3",
        "accessibility_gap": -14
      },
      {
        "id": "top-task-4",
        "accessibility_gap": -14
      },
      {
        "id": "top-task-5",
        "accessibility_gap": -14
      },
      {
        "id": "top-task-6",
        "accessibility_gap": -14
      }
    ],
    "summary": {
      "paired_services": 12,
      "missing_counterpart": 3,
      "average_absolute_accessibility_gap": 14
    }
  },
  "top_urls": [
    {
      "inventory_id": "curated-001-en",
      "id": "curated-001",
      "service_name": "Apply for a Social Insurance Number",
      "language": "en",
      "source": "unknown",
      "service_pattern": "application",
      "service_category": "identity",
      "institution": "ESDC",
      "page_load_count": 45000,
      "scan_status": "success",
      "failure_reason": null,
      "lighthouse": {
        "performance_score": 86,
        "accessibility_score": 72,
        "best_practices_score": 70,
        "seo_score": 60,
        "lcp_value_ms": 4445
      },
      "scangov": {
        "critical": 1,
        "serious": 3,
        "moderate": 1,
        "minor": 6
      }
    },
    {
      "inventory_id": "curated-001-fr",
      "id": "curated-001",
      "service_name": "Apply for a Social Insurance Number",
      "language": "fr",
      "source": "unknown",
      "service_pattern": "application",
      "service_category": "identity",
      "institution": "ESDC",
      "page_load_count": 45000,
      "scan_status": "success",
      "failure_reason": null,
      "lighthouse": {
        "performance_score": 45,
        "accessibility_score": 86,
        "best_practices_score": 78,
        "seo_score": 95,
        "lcp_value_ms": 1313
      },
      "scangov": {
        "critical": 0,
        "serious": 4,
        "moderate": 2,
        "minor": 5
      }
    },
    {
      "inventory_id": "curated-002-en",
      "id": "curated-002",
      "service_name": "Check my Service Canada Account",
      "language": "en",
      "source": "unknown",
      "service_pattern": "sign-in",
      "service_category": "account",
      "institution": "ESDC",
      "page_load_count": 170000,
      "scan_status": "success",
      "failure_reason": null,
      "lighthouse": {
        "performance_score": 86,
        "accessibility_score": 72,
        "best_practices_score": 70,
        "seo_score": 60,
        "lcp_value_ms": 4445
      },
      "scangov": {
        "critical": 1,
        "serious": 3,
        "moderate": 1,
        "minor": 6
      }
    },
    {
      "inventory_id": "curated-002-fr",
      "id": "curated-002",
      "service_name": "Check my Service Canada Account",
      "language": "fr",
      "source": "unknown",
      "service_pattern": "sign-in",
      "service_category": "account",
      "institution": "ESDC",
      "page_load_count": 170000,
      "scan_status": "success",
      "failure_reason": null,
      "lighthouse": {
        "performance_score": 45,
        "accessibility_score": 86,
        "best_practices_score": 78,
        "seo_score": 95,
        "lcp_value_ms": 1313
      },
      "scangov": {
        "critical": 0,
        "serious": 4,
        "moderate": 2,
        "minor": 5
      }
    },
    {
      "inventory_id": "curated-004-en",
      "id": "curated-004",
      "service_name": "Canada Border Wait Times",
      "language": "en",
      "source": "unknown",
      "service_pattern": "status",
      "service_category": "travel",
      "institution": "CBSA",
      "page_load_count": 94000,
      "scan_status": "success",
      "failure_reason": null,
      "lighthouse": {
        "performance_score": 86,
        "accessibility_score": 72,
        "best_practices_score": 70,
        "seo_score": 60,
        "lcp_value_ms": 4445
      },
      "scangov": {
        "critical": 1,
        "serious": 3,
        "moderate": 1,
        "minor": 6
      }
    },
    {
      "inventory_id": "curated-004-fr",
      "id": "curated-004",
      "service_name": "Canada Border Wait Times",
      "language": "fr",
      "source": "unknown",
      "service_pattern": "status",
      "service_category": "travel",
      "institution": "CBSA",
      "page_load_count": 94000,
      "scan_status": "success",
      "failure_reason": null,
      "lighthouse": {
        "performance_score": 45,
        "accessibility_score": 86,
        "best_practices_score": 78,
        "seo_score": 95,
        "lcp_value_ms": 1313
      },
      "scangov": {
        "critical": 0,
        "serious": 4,
        "moderate": 2,
        "minor": 5
      }
    },
    {
      "inventory_id": "curated-006-en",
      "id": "curated-006",
      "service_name": "Justice Laws Website",
      "language": "en",
      "source": "unknown",
      "service_pattern": "dashboard",
      "service_category": "information",
      "institution": "Justice",
      "page_load_count": 88000,
      "scan_status": "success",
      "failure_reason": null,
      "lighthouse": {
        "performance_score": 86,
        "accessibility_score": 72,
        "best_practices_score": 70,
        "seo_score": 60,
        "lcp_value_ms": 4445
      },
      "scangov": {
        "critical": 1,
        "serious": 3,
        "moderate": 1,
        "minor": 6
      }
    },
    {
      "inventory_id": "curated-006-fr",
      "id": "curated-006",
      "service_name": "Justice Laws Website",
      "language": "fr",
      "source": "unknown",
      "service_pattern": "dashboard",
      "service_category": "information",
      "institution": "Justice",
      "page_load_count": 88000,
      "scan_status": "success",
      "failure_reason": null,
      "lighthouse": {
        "performance_score": 45,
        "accessibility_score": 86,
        "best_practices_score": 78,
        "seo_score": 95,
        "lcp_value_ms": 1313
      },
      "scangov": {
        "critical": 0,
        "serious": 4,
        "moderate": 2,
        "minor": 5
      }
    },
    {
      "inventory_id": "curated-008-en",
      "id": "curated-008",
      "service_name": "IRCC: Apply for permanent residency",
      "language": "en",
      "source": "unknown",
      "service_pattern": "application",
      "service_category": "immigration",
      "institution": "IRCC",
      "page_load_count": 78000,
      "scan_status": "success",
      "failure_reason": null,
      "lighthouse": {
        "performance_score": 86,
        "accessibility_score": 72,
        "best_practices_score": 70,
        "seo_score": 60,
        "lcp_value_ms": 4445
      },
      "scangov": {
        "critical": 1,
        "serious": 3,
        "moderate": 1,
        "minor": 6
      }
    },
    {
      "inventory_id": "curated-008-fr",
      "id": "curated-008",
      "service_name": "IRCC: Apply for permanent residency",
      "language": "fr",
      "source": "unknown",
      "service_pattern": "application",
      "service_category": "immigration",
      "institution": "IRCC",
      "page_load_count": 78000,
      "scan_status": "success",
      "failure_reason": null,
      "lighthouse": {
        "performance_score": 45,
        "accessibility_score": 86,
        "best_practices_score": 78,
        "seo_score": 95,
        "lcp_value_ms": 1313
      },
      "scangov": {
        "critical": 0,
        "serious": 4,
        "moderate": 2,
        "minor": 5
      }
    },
    {
      "inventory_id": "curated-010-en",
      "id": "curated-010",
      "service_name": "Health Infobase Canada",
      "language": "en",
      "source": "unknown",
      "service_pattern": "information",
      "service_category": "health",
      "institution": "PHAC",
      "page_load_count": 65000,
      "scan_status": "success",
      "failure_reason": null,
      "lighthouse": {
        "performance_score": 86,
        "accessibility_score": 72,
        "best_practices_score": 70,
        "seo_score": 60,
        "lcp_value_ms": 4445
      },
      "scangov": {
        "critical": 1,
        "serious": 3,
        "moderate": 1,
        "minor": 6
      }
    },
    {
      "inventory_id": "curated-010-fr",
      "id": "curated-010",
      "service_name": "Health Infobase Canada",
      "language": "fr",
      "source": "unknown",
      "service_pattern": "information",
      "service_category": "health",
      "institution": "PHAC",
      "page_load_count": 65000,
      "scan_status": "success",
      "failure_reason": null,
      "lighthouse": {
        "performance_score": 45,
        "accessibility_score": 86,
        "best_practices_score": 78,
        "seo_score": 95,
        "lcp_value_ms": 1313
      },
      "scangov": {
        "critical": 0,
        "serious": 4,
        "moderate": 2,
        "minor": 5
      }
    },
    {
      "inventory_id": "recent-0-en",
      "id": "recent-0",
      "service_name": "Sign in to your CRA account",
      "language": "en",
      "canonical_url": "https://www.canada.ca/en/revenue-agency/services/e-services/cra-login-services.html",
      "source": "recent",
      "service_pattern": "unknown",
      "service_category": "tax",
      "institution": null,
      "page_load_count": 39167494,
      "scan_status": "success",
      "failure_reason": null,
      "lighthouse": {
        "performance_score": 74,
        "accessibility_score": 66,
        "best_practices_score": 69,
        "seo_score": 83,
        "lcp_value_ms": 2593
      },
      "scangov": {
        "critical": 0,
        "serious": 2,
        "moderate": 0,
        "minor": 5
      }
    },
    {
      "inventory_id": "recent-1-en",
      "id": "recent-1",
      "service_name": "Canada Revenue Agency - CRA Sign-in",
      "language": "en",
      "canonical_url": "https://cms-sgj.cra-arc.gc.ca/gol-ged/awsc/cms/login",
      "source": "recent,recent",
      "service_pattern": "unknown",
      "service_category": "tax",
      "institution": null,
      "page_load_count": 22675340,
      "scan_status": "success",
      "failure_reason": null,
      "lighthouse": {
        "performance_score": 72,
        "accessibility_score": 85,
        "best_practices_score": 71,
        "seo_score": 72,
        "lcp_value_ms": 1370
      },
      "scangov": {
        "critical": 1,
        "serious": 0,
        "moderate": 7,
        "minor": 5
      }
    },
    {
      "inventory_id": "recent-2-en",
      "id": "recent-2",
      "service_name": "Canada Revenue Agency - CRA sign-in information",
      "language": "en",
      "canonical_url": "https://cms-sgj.cra-arc.gc.ca/gol-ged/awsc/cms/postlogin/welcome",
      "source": "recent,recent",
      "service_pattern": "unknown",
      "service_category": "tax",
      "institution": null,
      "page_load_count": 17708535,
      "scan_status": "success",
      "failure_reason": null,
      "lighthouse": {
        "performance_score": 73,
        "accessibility_score": 85,
        "best_practices_score": 91,
        "seo_score": 68,
        "lcp_value_ms": 1311
      },
      "scangov": {
        "critical": 0,
        "serious": 3,
        "moderate": 0,
        "minor": 12
      }
    },
    {
      "inventory_id": "top-task-1-en",
      "id": "top-task-1",
      "service_name": "Personal income tax",
      "language": "en",
      "source": "top-task",
      "service_pattern": "application",
      "service_category": "tax",
      "institution": "CRA",
      "page_load_count": 460000,
      "scan_status": "success",
      "failure_reason": null,
      "lighthouse": {
        "performance_score": 86,
        "accessibility_score": 72,
        "best_practices_score": 70,
        "seo_score": 60,
        "lcp_value_ms": 4445
      },
      "scangov": {
        "critical": 1,
        "serious": 3,
        "moderate": 1,
        "minor": 6
      }
    },
    {
      "inventory_id": "top-task-1-fr",
      "id": "top-task-1",
      "service_name": "Personal income tax",
      "language": "fr",
      "source": "top-task",
      "service_pattern": "application",
      "service_category": "tax",
      "institution": "CRA",
      "page_load_count": 460000,
      "scan_status": "success",
      "failure_reason": null,
      "lighthouse": {
        "performance_score": 45,
        "accessibility_score": 86,
        "best_practices_score": 78,
        "seo_score": 95,
        "lcp_value_ms": 1313
      },
      "scangov": {
        "critical": 0,
        "serious": 4,
        "moderate": 2,
        "minor": 5
      }
    },
    {
      "inventory_id": "top-task-2-en",
      "id": "top-task-2",
      "service_name": "Job search and benefits",
      "language": "en",
      "source": "top-task",
      "service_pattern": "dashboard",
      "service_category": "employment",
      "institution": "ESDC",
      "page_load_count": 420000,
      "scan_status": "success",
      "failure_reason": null,
      "lighthouse": {
        "performance_score": 86,
        "accessibility_score": 72,
        "best_practices_score": 70,
        "seo_score": 60,
        "lcp_value_ms": 4445
      },
      "scangov": {
        "critical": 1,
        "serious": 3,
        "moderate": 1,
        "minor": 6
      }
    },
    {
      "inventory_id": "top-task-2-fr",
      "id": "top-task-2",
      "service_name": "Job search and benefits",
      "language": "fr",
      "source": "top-task",
      "service_pattern": "dashboard",
      "service_category": "employment",
      "institution": "ESDC",
      "page_load_count": 420000,
      "scan_status": "success",
      "failure_reason": null,
      "lighthouse": {
        "performance_score": 45,
        "accessibility_score": 86,
        "best_practices_score": 78,
        "seo_score": 95,
        "lcp_value_ms": 1313
      },
      "scangov": {
        "critical": 0,
        "serious": 4,
        "moderate": 2,
        "minor": 5
      }
    },
    {
      "inventory_id": "top-task-3-en",
      "id": "top-task-3",
      "service_name": "Passport and travel",
      "language": "en",
      "source": "top-task",
      "service_pattern": "help",
      "service_category": "travel",
      "institution": "IRCC",
      "page_load_count": 380000,
      "scan_status": "success",
      "failure_reason": null,
      "lighthouse": {
        "performance_score": 86,
        "accessibility_score": 72,
        "best_practices_score": 70,
        "seo_score": 60,
        "lcp_value_ms": 4445
      },
      "scangov": {
        "critical": 1,
        "serious": 3,
        "moderate": 1,
        "minor": 6
      }
    },
    {
      "inventory_id": "top-task-3-fr",
      "id": "top-task-3",
      "service_name": "Passport and travel",
      "language": "fr",
      "source": "top-task",
      "service_pattern": "help",
      "service_category": "travel",
      "institution": "IRCC",
      "page_load_count": 380000,
      "scan_status": "success",
      "failure_reason": null,
      "lighthouse": {
        "performance_score": 45,
        "accessibility_score": 86,
        "best_practices_score": 78,
        "seo_score": 95,
        "lcp_value_ms": 1313
      },
      "scangov": {
        "critical": 0,
        "serious": 4,
        "moderate": 2,
        "minor": 5
      }
    },
    {
      "inventory_id": "top-task-4-en",
      "id": "top-task-4",
      "service_name": "Student loans and grants",
      "language": "en",
      "source": "top-task",
      "service_pattern": "application",
      "service_category": "education",
      "institution": "ESDC",
      "page_load_count": 340000,
      "scan_status": "success",
      "failure_reason": null,
      "lighthouse": {
        "performance_score": 86,
        "accessibility_score": 72,
        "best_practices_score": 70,
        "seo_score": 60,
        "lcp_value_ms": 4445
      },
      "scangov": {
        "critical": 1,
        "serious": 3,
        "moderate": 1,
        "minor": 6
      }
    },
    {
      "inventory_id": "top-task-4-fr",
      "id": "top-task-4",
      "service_name": "Student loans and grants",
      "language": "fr",
      "source": "top-task",
      "service_pattern": "application",
      "service_category": "education",
      "institution": "ESDC",
      "page_load_count": 340000,
      "scan_status": "success",
      "failure_reason": null,
      "lighthouse": {
        "performance_score": 45,
        "accessibility_score": 86,
        "best_practices_score": 78,
        "seo_score": 95,
        "lcp_value_ms": 1313
      },
      "scangov": {
        "critical": 0,
        "serious": 4,
        "moderate": 2,
        "minor": 5
      }
    },
    {
      "inventory_id": "top-task-5-en",
      "id": "top-task-5",
      "service_name": "COVID-19 information",
      "language": "en",
      "source": "top-task",
      "service_pattern": "information",
      "service_category": "health",
      "institution": "PHAC",
      "page_load_count": 300000,
      "scan_status": "success",
      "failure_reason": null,
      "lighthouse": {
        "performance_score": 86,
        "accessibility_score": 72,
        "best_practices_score": 70,
        "seo_score": 60,
        "lcp_value_ms": 4445
      },
      "scangov": {
        "critical": 1,
        "serious": 3,
        "moderate": 1,
        "minor": 6
      }
    },
    {
      "inventory_id": "top-task-5-fr",
      "id": "top-task-5",
      "service_name": "COVID-19 information",
      "language": "fr",
      "source": "top-task",
      "service_pattern": "information",
      "service_category": "health",
      "institution": "PHAC",
      "page_load_count": 300000,
      "scan_status": "success",
      "failure_reason": null,
      "lighthouse": {
        "performance_score": 45,
        "accessibility_score": 86,
        "best_practices_score": 78,
        "seo_score": 95,
        "lcp_value_ms": 1313
      },
      "scangov": {
        "critical": 0,
        "serious": 4,
        "moderate": 2,
        "minor": 5
      }
    },
    {
      "inventory_id": "top-task-6-en",
      "id": "top-task-6",
      "service_name": "Immigration and citizenship",
      "language": "en",
      "source": "top-task",
      "service_pattern": "application",
      "service_category": "immigration",
      "institution": "IRCC",
      "page_load_count": 260000,
      "scan_status": "success",
      "failure_reason": null,
      "lighthouse": {
        "performance_score": 86,
        "accessibility_score": 72,
        "best_practices_score": 70,
        "seo_score": 60,
        "lcp_value_ms": 4445
      },
      "scangov": {
        "critical": 1,
        "serious": 3,
        "moderate": 1,
        "minor": 6
      }
    },
    {
      "inventory_id": "top-task-6-fr",
      "id": "top-task-6",
      "service_name": "Immigration and citizenship",
      "language": "fr",
      "source": "top-task",
      "service_pattern": "application",
      "service_category": "immigration",
      "institution": "IRCC",
      "page_load_count": 260000,
      "scan_status": "success",
      "failure_reason": null,
      "lighthouse": {
        "performance_score": 45,
        "accessibility_score": 86,
        "best_practices_score": 78,
        "seo_score": 95,
        "lcp_value_ms": 1313
      },
      "scangov": {
        "critical": 0,
        "serious": 4,
        "moderate": 2,
        "minor": 5
      }
    }
  ],
  "methodology": {
    "status": "baseline",
    "note": "Phase 1 baseline with deterministic mock/live scanner adapters; impact and statement sections are planned for later phases."
  },
  "output_paths": {
    "daily_dir": "docs/reports/daily/2026-03-25/",
    "report_json": "docs/reports/daily/2026-03-25/report.json",
    "report_html": "docs/reports/daily/2026-03-25/index.html",
    "dashboard_html": "docs/reports/index.html"
  }
}
